llamalabs/__init__.py
llamalabs/agents/__init__.py
llamalabs/agents/api.py
llamalabs/agents/code_shot.py
llamalabs/agents/code_shot_test.py
llamalabs/agents/utils.py
llamalabs/agents/utils_test.py
llamalabs/client/__init__.py
llamalabs/client/client.py
llamalabs/client/client_test.py
llamalabs/client/console.py
llamalabs/client/session.py
llamalabs-0.1.1.dist-info/entry_points.txt
llamalabs-0.1.1.dist-info/LICENSE
llamalabs-0.1.1.dist-info/WHEEL
llamalabs-0.1.1.dist-info/METADATA
llamalabs-0.1.1.dist-info/RECORD
