Metadata-Version: 2.1
Name: llamalabs
Version: 0.1.1
Summary: SDK for the Llama Labs platform. See: https://llamalabs.ai
Author: LlamaLabs.ai Team
Author-email: info@llamalabs.ai
Requires-Python: >=3.9,<4.0
Classifier: Programming Language :: Python :: 3
Classifier: Programming Language :: Python :: 3.9
Classifier: Programming Language :: Python :: 3.10
Requires-Dist: PyYAML (>=6.0,<7.0)
Requires-Dist: click (>=8.1.3,<9.0.0)
Requires-Dist: fastapi[all] (>=0.89.1,<0.90.0)
Requires-Dist: gql[all] (>=3.4.0,<4.0.0)
Requires-Dist: pillow (>=9.0.1,<10.0.0)
Requires-Dist: prompt-toolkit (>=3.0.31,<4.0.0)
Requires-Dist: pydantic
Requires-Dist: requests (>=2.28.1,<3.0.0)
Requires-Dist: rich (>=12.6.0,<13.0.0)
